medaimodels/__init__.py
medaimodels-0.0.7.dist-info/METADATA
medaimodels-0.0.7.dist-info/WHEEL
medaimodels-0.0.7.dist-info/top_level.txt
medaimodels-0.0.7.dist-info/RECORD
