Metadata-Version: 2.1
Name: medaimodels
Version: 0.0.7
Summary: A libarary for creating med-ai models
Home-page: UNKNOWN
Author: ['Travis Clarke', 'Jacob Clarke']
Author-email: travisjonathanclarke@gmail.com
License: Apache-1.0
Platform: UNKNOWN
Requires-Dist: pylint
Requires-Dist: scikit-image
Requires-Dist: sphinx
